sudo/__init__.py
sudo/decorators.py
sudo/forms.py
sudo/middleware.py
sudo/mixins.py
sudo/models.py
sudo/settings.py
sudo/signals.py
sudo/utils.py
sudo/views.py
django_sudo-3.1.0.dist-info/LICENSE
django_sudo-3.1.0.dist-info/METADATA
django_sudo-3.1.0.dist-info/WHEEL
django_sudo-3.1.0.dist-info/top_level.txt
django_sudo-3.1.0.dist-info/zip-safe
django_sudo-3.1.0.dist-info/RECORD
